senticnet/__init__.py
senticnet/babelsenticnet.py
senticnet/senticnet.py
senticnet/senticnet6.py
senticnet/babel/__init__.py
senticnet/babel/senticnet_ar.py
senticnet/babel/senticnet_ba.py
senticnet/babel/senticnet_bg.py
senticnet/babel/senticnet_ca.py
senticnet/babel/senticnet_cn.py
senticnet/babel/senticnet_cz.py
senticnet/babel/senticnet_de.py
senticnet/babel/senticnet_dk.py
senticnet/babel/senticnet_ee.py
senticnet/babel/senticnet_es.py
senticnet/babel/senticnet_fi.py
senticnet/babel/senticnet_fr.py
senticnet/babel/senticnet_gr.py
senticnet/babel/senticnet_he.py
senticnet/babel/senticnet_hi.py
senticnet/babel/senticnet_hm.py
senticnet/babel/senticnet_hr.py
senticnet/babel/senticnet_ht.py
senticnet/babel/senticnet_hu.py
senticnet/babel/senticnet_id.py
senticnet/babel/senticnet_it.py
senticnet/babel/senticnet_jp.py
senticnet/babel/senticnet_kr.py
senticnet/babel/senticnet_lt.py
senticnet/babel/senticnet_lv.py
senticnet/babel/senticnet_mt.py
senticnet/babel/senticnet_my.py
senticnet/babel/senticnet_nl.py
senticnet/babel/senticnet_pt.py
senticnet/babel/senticnet_ro.py
senticnet/babel/senticnet_rs.py
senticnet/babel/senticnet_ru.py
senticnet/babel/senticnet_se.py
senticnet/babel/senticnet_sg.py
senticnet/babel/senticnet_si.py
senticnet/babel/senticnet_sk.py
senticnet/babel/senticnet_th.py
senticnet/babel/senticnet_tr.py
senticnet/babel/senticnet_ua.py
senticnet/babel/senticnet_ur.py
senticnet-1.6.dist-info/LICENSE
senticnet-1.6.dist-info/METADATA
senticnet-1.6.dist-info/WHEEL
senticnet-1.6.dist-info/top_level.txt
senticnet-1.6.dist-info/RECORD
