Metadata-Version: 2.1
Name: senticnet
Version: 1.6
Summary: Access SenticNet data using Python
Home-page: https://github.com/yurimalheiros/senticnetapi
Author: Yuri Malheiros
Author-email: yuri@dcx.ufpb.br
License: UNKNOWN
Platform: UNKNOWN
Classifier: Development Status :: 5 - Production/Stable
Classifier: Intended Audience :: Science/Research
Classifier: License :: OSI Approved :: MIT License
Classifier: Operating System :: OS Independent
Classifier: Programming Language :: Python
Classifier: Topic :: Software Development :: Libraries
